pyshell2/__init__.py
pyshell2/asyncdocker.py
pyshell2/asyncshell.py
pyshell2/docker.py
pyshell2/shell.py
pyshell2-0.1.1.dist-info/LICENSE.md
pyshell2-0.1.1.dist-info/METADATA
pyshell2-0.1.1.dist-info/WHEEL
pyshell2-0.1.1.dist-info/top_level.txt
pyshell2-0.1.1.dist-info/RECORD
